itertools.py
setup.py
micropython_itertools.egg-info/PKG-INFO
micropython_itertools.egg-info/SOURCES.txt
micropython_itertools.egg-info/dependency_links.txt
micropython_itertools.egg-info/top_level.txt